setup.py
pho/__init__.py
pho/models.py
pho.egg-info/PKG-INFO
pho.egg-info/SOURCES.txt
pho.egg-info/dependency_links.txt
pho.egg-info/requires.txt
pho.egg-info/top_level.txt