Metadata-Version: 1.0
Name: pho
Version: 0.0.3
Summary: High performance HTML parser built on lxml
Home-page: http://stylrapp.com
Author: Eytan Daniyalzade
Author-email: eytan@stylrapp.com
License: UNKNOWN
Platform: UNKNOWN
